CREDITS.md
LICENSE.md
MANIFEST.in
README.rst
VERSION
setup.cfg
setup.py
app/__init__.py
app/contexts.py
app/debug.py
app/engines.py
app/inputs.py
app/latches.py
app/nets.py
app/simulators.py
app/traces.py
app/upload.py
app/utils.py
app/tests/__init__.py
app/tests/test_contexts.py
app/tests/test_engines.py
app/tests/test_inputs.py
app/tests/test_latches.py
app/tests/test_nets.py
app/tests/test_simulators.py
app/tests/test_upload.py
intrepyd/__init__.py
intrepyd/api.py
intrepyd/circuit.py
intrepyd/context.py
intrepyd/engine.py
intrepyd/parser.py
intrepyd/plots.py
intrepyd/pseudoboolean.py
intrepyd/scr.py
intrepyd/simulator.py
intrepyd/tools.py
intrepyd/trace.py
intrepyd/visitable.py
intrepyd.egg-info/PKG-INFO
intrepyd.egg-info/SOURCES.txt
intrepyd.egg-info/dependency_links.txt
intrepyd.egg-info/requires.txt
intrepyd.egg-info/top_level.txt
intrepyd/atg/__init__.py
intrepyd/atg/circuit.py
intrepyd/atg/mcdc.py
intrepyd/components/__init__.py
intrepyd/components/eda.py
intrepyd/iec611312py/IEC61131ParserLexer.py
intrepyd/iec611312py/IEC61131ParserParser.py
intrepyd/iec611312py/IEC61131ParserVisitor.py
intrepyd/iec611312py/__init__.py
intrepyd/iec611312py/datatype.py
intrepyd/iec611312py/expression.py
intrepyd/iec611312py/flatstmt2intrepyd.py
intrepyd/iec611312py/flattener.py
intrepyd/iec611312py/function.py
intrepyd/iec611312py/functionblock.py
intrepyd/iec611312py/inferdatatype.py
intrepyd/iec611312py/parsest.py
intrepyd/iec611312py/plcopen.py
intrepyd/iec611312py/statement.py
intrepyd/iec611312py/stmtbuilder.py
intrepyd/iec611312py/stmtprinter.py
intrepyd/iec611312py/summarizer.py
intrepyd/iec611312py/translator.py
intrepyd/iec611312py/utils.py
intrepyd/iec611312py/variable.py
intrepyd/iec611312py/visitor.py
intrepyd/lustre2py/LustreLexer.py
intrepyd/lustre2py/LustreParser.py
intrepyd/lustre2py/LustreVisitor.py
intrepyd/lustre2py/__init__.py
intrepyd/lustre2py/ast.py
intrepyd/lustre2py/ast2intrepyd.py
intrepyd/lustre2py/astbuilder.py
intrepyd/lustre2py/astprinter.py
intrepyd/lustre2py/datatype.py
intrepyd/lustre2py/expression.py
intrepyd/lustre2py/instruction.py
intrepyd/lustre2py/node.py
intrepyd/lustre2py/parser.py
