Metadata-Version: 2.1
Name: intrepyd
Version: 0.12.0
Summary: Intrepyd Model Checker
Home-page: http://github.com/formalmethods/intrepid
Author: Roberto Bruttomesso
Author-email: roberto.bruttomesso@gmail.com
Maintainer: Roberto Bruttomesso
Maintainer-email: roberto.bruttomesso@gmail.com
License: BSD-3-Clause
Download-URL: http://github.com/formalmethods/intrepid/archive/0.12.0.tar.gz
Platform: Windows
Platform: Linux
Platform: Darwin
License-File: LICENSE.md
